lndb_schema_core/__init__.py
lndb_schema_core/_core.py
lndb_schema_core/id.py
lndb_schema_core-0.3.1.dist-info/LICENSE
lndb_schema_core-0.3.1.dist-info/WHEEL
lndb_schema_core-0.3.1.dist-info/METADATA
lndb_schema_core-0.3.1.dist-info/RECORD
